DyGAF/__init__.py
DyGAF/analyze_feature_importance.py
DyGAF/dependent_attention_model_pipeline.py
DyGAF/independent_attention_model_pipeline.py
DyGAF/main.py
DyGAF-0.0.3.dist-info/METADATA
DyGAF-0.0.3.dist-info/WHEEL
DyGAF-0.0.3.dist-info/entry_points.txt
DyGAF-0.0.3.dist-info/top_level.txt
DyGAF-0.0.3.dist-info/RECORD
